ciptest/__init__.py
ciptest/__main__.py
ciptest/cip_exceptions.py
ciptest/client_api.py
ciptest/exception.py
ciptest/exceptions.py
ciptest/func.py
ciptest-1.0.9.6.dist-info/METADATA
ciptest-1.0.9.6.dist-info/WHEEL
ciptest-1.0.9.6.dist-info/entry_points.txt
ciptest-1.0.9.6.dist-info/top_level.txt
ciptest-1.0.9.6.dist-info/RECORD
