Metadata-Version: 2.1
Name: ciptest
Version: 1.0.9.6
Summary: Criminal IP Package Test
Home-page: https://www.criminalip.io/ko
Author: tygo
Author-email: tygo@aispera.com
License: UNKNOWN
Platform: UNKNOWN
Requires-Dist: requests (>=2.2.1)
Requires-Dist: click
